llm_replicate/__init__.py
llm_replicate-0.3.1.dist-info/LICENSE
llm_replicate-0.3.1.dist-info/METADATA
llm_replicate-0.3.1.dist-info/WHEEL
llm_replicate-0.3.1.dist-info/entry_points.txt
llm_replicate-0.3.1.dist-info/top_level.txt
llm_replicate-0.3.1.dist-info/RECORD
