Metadata-Version: 2.1
Name: llm-replicate
Version: 0.3.1
Summary: LLM plugin for models hosted on Replicate
Author: Simon Willison
License: Apache-2.0
Project-URL: Homepage, https://github.com/simonw/llm-replicate
Project-URL: Changelog, https://github.com/simonw/llm-replicate/releases
Project-URL: Issues, https://github.com/simonw/llm-replicate/issues
Classifier: License :: OSI Approved :: Apache Software License
Requires-Python: >3.7
License-File: LICENSE
Requires-Dist: llm
Requires-Dist: requests-mock
Requires-Dist: replicate >=0.9.0
Provides-Extra: test
Requires-Dist: pytest ; extra == 'test'
